{
  "productos": [
    {
      "nombre": "Café Espresso",
      "precio": 2.5,
      "categoria": "Bebidas",
      "imagen": "img/espresso.jpg"
    },
    {
      "nombre": "Capuchino",
      "precio": 3.0,
      "categoria": "Bebidas",
      "imagen": "img/capuchino.jpg"
    },
    {
      "nombre": "Croissant",
      "precio": 1.5,
      "categoria": "Panadería",
      "imagen": "img/croissant.jpg"
    },
    {
      "nombre": "Tarta de Chocolate",
      "precio": 4.0,
      "categoria": "Repostería",
      "imagen": "img/tarta_chocolate.jpg"
    },
    {
      "nombre": "Latte",
      "precio": 3.5,
      "categoria": "Bebidas",
      "imagen": "img/latte.jpg"
    },
    {
      "nombre": "Americano",
      "precio": 2.0,
      "categoria": "Bebidas",
      "imagen": "img/americano.jpg"
    },
    {
      "nombre": "Bagel",
      "precio": 2.5,
      "categoria": "Panadería",
      "imagen": "img/bagel.jpg"
    },
    {
      "nombre": "Sándwich de Jamón y Queso",
      "precio": 3.5,
      "categoria": "Panadería",
      "imagen": "img/sandwich.jpg"
    },
    {
      "nombre": "Brownie",
      "precio": 2.0,
      "categoria": "Repostería",
      "imagen": "img/brownie.jpg"
    },
    {
      "nombre": "Muffin de Arándanos",
      "precio": 2.5,
      "categoria": "Repostería",
      "imagen": "img/muffin_arandanos.jpg"
    },
    {
      "nombre": "Té Verde",
      "precio": 2.0,
      "categoria": "Bebidas",
      "imagen": "img/te_verde.jpg"
    },
    {
      "nombre": "Té Negro",
      "precio": 2.0,
      "categoria": "Bebidas",
      "imagen": "img/te_negro.jpg"
    },
    {
      "nombre": "Café Mocha",
      "precio": 3.8,
      "categoria": "Bebidas",
      "imagen": "img/mocha.jpg"
    },
    {
      "nombre": "Café con Leche",
      "precio": 3.0,
      "categoria": "Bebidas",
      "imagen": "img/cafe_leche.jpg"
    },
    {
      "nombre": "Pan de Banana",
      "precio": 2.5,
      "categoria": "Panadería",
      "imagen": "img/pan_banana.jpg"
    },
    {
      "nombre": "Donut Glaseado",
      "precio": 1.8,
      "categoria": "Panadería",
      "imagen": "img/donut.jpg"
    },
    {
      "nombre": "Cheesecake",
      "precio": 3.5,
      "categoria": "Repostería",
      "imagen": "img/cheesecake.jpg"
    },
    {
      "nombre": "Macaron",
      "precio": 1.5,
      "categoria": "Repostería",
      "imagen": "img/macaron.jpg"
    }
  ]
}
